vpextractor/__init__.py
vpextractor/_utils.py
vpextractor/data.py
vpextractor/disable_key.mplstyle
vpextractor/drawing.py
vpextractor/fileio.py
vpextractor/filter.py
vpextractor/generalUI.py
vpextractor/mplui.py
vpextractor/utils.py
vector_plot_extractor-0.1.3.dist-info/LICENSE
vector_plot_extractor-0.1.3.dist-info/METADATA
vector_plot_extractor-0.1.3.dist-info/WHEEL
vector_plot_extractor-0.1.3.dist-info/entry_points.txt
vector_plot_extractor-0.1.3.dist-info/top_level.txt
vector_plot_extractor-0.1.3.dist-info/RECORD
