Metadata-Version: 2.1
Name: vector-plot-extractor
Version: 0.1.3
Summary: tools for extracting data from vector plots
Author-email: Yu-Chen Wang <ycwang-astro@users.noreply.github.com>
Project-URL: Homepage, https://github.com/ycwang-astro/vector-plot-extractor
Project-URL: Documentation, https://github.com/ycwang-astro/vector-plot-extractor
Project-URL: Repository, https://github.com/ycwang-astro/vector-plot-extractor.git
Project-URL: Issues, https://github.com/ycwang-astro/vector-plot-extractor/issues
Project-URL: Changelog, https://github.com/ycwang-astro/vector-plot-extractor/blob/main/CHANGELOG.md
Keywords: vector graphic,vector plot,extractor,digitizer
Classifier: Development Status :: 3 - Alpha
Classifier: Programming Language :: Python :: 3
Classifier: License :: OSI Approved :: GNU General Public License v3 (GPLv3)
Classifier: Intended Audience :: Science/Research
License-File: LICENSE
Requires-Dist: matplotlib
Requires-Dist: numpy
Requires-Dist: pymupdf
